postgresdave_package/.querylog
postgresdave_package/__init__.py
postgresdave_package/postgresdave.py
postgresdave_package/testcase1.csv
postgresdave_package-2.0.4.dist-info/METADATA
postgresdave_package-2.0.4.dist-info/WHEEL
postgresdave_package-2.0.4.dist-info/licenses/LICENSE
postgresdave_package-2.0.4.dist-info/RECORD
